pyspect/__init__.py
pyspect-0.0.0.dist-info/METADATA
pyspect-0.0.0.dist-info/WHEEL
pyspect-0.0.0.dist-info/licenses/LICENSE
pyspect-0.0.0.dist-info/RECORD
